idoitapi/API.py
idoitapi/APIException.py
idoitapi/CMDBCategory.py
idoitapi/CMDBCategoryInfo.py
idoitapi/CMDBCondition.py
idoitapi/CMDBDialog.py
idoitapi/CMDBImpact.py
idoitapi/CMDBLocationTree.py
idoitapi/CMDBLogbook.py
idoitapi/CMDBObject.py
idoitapi/CMDBObjectTypeCategories.py
idoitapi/CMDBObjectTypeGroups.py
idoitapi/CMDBObjectTypes.py
idoitapi/CMDBObjects.py
idoitapi/CMDBObjectsByRelation.py
idoitapi/CMDBReports.py
idoitapi/CMDBStatus.py
idoitapi/CMDBWorkstationComponents.py
idoitapi/CheckMKStaticTag.py
idoitapi/CheckMKTags.py
idoitapi/File.py
idoitapi/Idoit.py
idoitapi/Image.py
idoitapi/MonitoringLivestatus.py
idoitapi/Request.py
idoitapi/Select.py
idoitapi/Subnet.py
idoitapi/__init__.py
idoitapi/utils.py
idoitapi/Console/Auth.py
idoitapi/Console/Console.py
idoitapi/Console/Import.py
idoitapi/Console/LDAP.py
idoitapi/Console/Logbook.py
idoitapi/Console/Notifications.py
idoitapi/Console/Report.py
idoitapi/Console/Search.py
idoitapi/Console/System.py
idoitapi/Console/__init__.py
idoitapi-1.0b7.dist-info/LICENSE
idoitapi-1.0b7.dist-info/METADATA
idoitapi-1.0b7.dist-info/WHEEL
idoitapi-1.0b7.dist-info/top_level.txt
idoitapi-1.0b7.dist-info/RECORD
